src/__init__.py
src/pyproject.toml
src/sshc.py
sshc-2.0.1.dist-info/LICENSE
sshc-2.0.1.dist-info/METADATA
sshc-2.0.1.dist-info/WHEEL
sshc-2.0.1.dist-info/entry_points.txt
sshc-2.0.1.dist-info/RECORD
