Metadata-Version: 2.1
Name: sshc
Version: 2.0.1
Summary: SSH Config and Ansible Inventory Generator.
Home-page: https://github.com/fahadahammed/sshc
License: MIT
Keywords: packaging,poetry
Author: fahadahammed
Author-email: iamfahadahammed@gmail.com
Requires-Python: >=3.7,<4.0
Classifier: Development Status :: 5 - Production/Stable
Classifier: Environment :: Console
Classifier: License :: OSI Approved :: MIT License
Classifier: Programming Language :: Python
Classifier: Programming Language :: Python :: 3
Classifier: Programming Language :: Python :: 3.7
Classifier: Programming Language :: Python :: 3.8
Classifier: Programming Language :: Python :: 3.9
Classifier: Programming Language :: Python :: 3.10
Classifier: Programming Language :: Python :: 3.11
Classifier: Programming Language :: Python :: 3.12
Classifier: Topic :: System :: Systems Administration
Requires-Dist: pyyaml (>=6.0,<7.0)
Project-URL: Documentation, https://github.com/fahadahammed/sshc
Project-URL: Repository, https://github.com/fahadahammed/sshc
